onavdata/__init__.py
onavdata/onavdata.py
onavdata/configs/config.toml
onavdata/data/shortnames.txt
onavdata/data/2014-09-09 UofMN Conservancy 7 UAV Flights/meta.toml
onavdata/data/2014-09-09 UofMN Conservancy 7 UAV Flights/meta_GPSFASER1.toml
onavdata/data/2014-09-09 UofMN Conservancy 7 UAV Flights/umn-uav-thor-2012-08-07.jpg
onavdata/data/2014-09-09 UofMN Conservancy 7 UAV Flights/Processed and Parsed Data/FASER-Flight-5/accel_data.txt.zip
onavdata/data/2014-09-09 UofMN Conservancy 7 UAV Flights/Processed and Parsed Data/FASER-Flight-5/baroalt_data.txt.zip
onavdata/data/2014-09-09 UofMN Conservancy 7 UAV Flights/Processed and Parsed Data/FASER-Flight-5/control_input_data.txt.zip
onavdata/data/2014-09-09 UofMN Conservancy 7 UAV Flights/Processed and Parsed Data/FASER-Flight-5/gps_traj_data.txt.zip
onavdata/data/2014-09-09 UofMN Conservancy 7 UAV Flights/Processed and Parsed Data/FASER-Flight-5/gps_velocity_data.txt.zip
onavdata/data/2014-09-09 UofMN Conservancy 7 UAV Flights/Processed and Parsed Data/FASER-Flight-5/gyro_data.txt.zip
onavdata/data/2014-09-09 UofMN Conservancy 7 UAV Flights/Processed and Parsed Data/FASER-Flight-5/mag_data.txt.zip
onavdata/data/2014-09-09 UofMN Conservancy 7 UAV Flights/Processed and Parsed Data/FASER-Flight-5/nav_attitude_data.txt.zip
onavdata/data/2014-09-09 UofMN Conservancy 7 UAV Flights/Processed and Parsed Data/FASER-Flight-5/nav_traj_data.txt.zip
onavdata/data/2014-09-09 UofMN Conservancy 7 UAV Flights/Processed and Parsed Data/FASER-Flight-5/speed_data.txt.zip
onavdata/data/2014-09-09 UofMN Conservancy 7 UAV Flights/Processed and Parsed Data/GPSFASER-Flight-1/accel_data.txt.zip
onavdata/data/2014-09-09 UofMN Conservancy 7 UAV Flights/Processed and Parsed Data/GPSFASER-Flight-1/baroalt_data.txt.zip
onavdata/data/2014-09-09 UofMN Conservancy 7 UAV Flights/Processed and Parsed Data/GPSFASER-Flight-1/control_input_data.txt.zip
onavdata-0.2.5.dist-info/METADATA
onavdata-0.2.5.dist-info/WHEEL
onavdata-0.2.5.dist-info/top_level.txt
onavdata-0.2.5.dist-info/RECORD
