Metadata-Version: 2.1
Name: onavdata
Version: 0.2.5
Summary: Easily import both reference and user-specified datasets for navigation system design and testing projects.
Author: Organic Navigation
Author-email: team@organicnavigation.com
Requires-Dist: toml
Requires-Dist: pandas
Requires-Dist: numpy
Requires-Dist: idelib (==3.1.0)
